{
  "formatVersion": "1.1",
  "component": {
    "group": "com.connection",
    "module": "buffer-service",
    "version": "1.0.0",
    "attributes": {
      "org.gradle.status": "release"
    }
  },
  "createdBy": {
    "gradle": {
      "version": "8.13"
    }
  },
  "variants": [
    {
      "name": "apiElements",
      "attributes": {
        "org.gradle.category": "library",
        "org.gradle.dependency.bundling": "external",
        "org.gradle.jvm.version": 21,
        "org.gradle.libraryelements": "jar",
        "org.gradle.usage": "java-api"
      },
      "files": [
        {
          "name": "buffer-service-1.0.0-plain.jar",
          "url": "buffer-service-1.0.0-plain.jar",
          "size": 30786,
          "sha512": "210523b8b44a6062603b12c9bff0b8b5693d8413db1556c78480dea9608c05534a49f82dd33b3606ca701a26c0a57ffd02f0c3b739e37067be5a32fcc0be47f1",
          "sha256": "4599c205c30ae3cb205c2a5ef82520b40b1c398cb211eed83a23825a6b9028af",
          "sha1": "bf16b62f956e2aca8b2849c2c194c0ee649ed200",
          "md5": "8d74e3d5728b6b212486d4d45854fe47"
        }
      ]
    },
    {
      "name": "runtimeElements",
      "attributes": {
        "org.gradle.category": "library",
        "org.gradle.dependency.bundling": "external",
        "org.gradle.jvm.version": 21,
        "org.gradle.libraryelements": "jar",
        "org.gradle.usage": "java-runtime"
      },
      "dependencies": [
        {
          "group": "org.springframework.data",
          "module": "spring-data-commons"
        },
        {
          "group": "org.springframework.boot",
          "module": "spring-boot-starter-jdbc"
        },
        {
          "group": "org.springframework.boot",
          "module": "spring-boot-starter-web"
        },
        {
          "group": "org.springframework.cloud",
          "module": "spring-cloud-starter-openfeign",
          "version": {
            "requires": "4.3.0"
          }
        },
        {
          "group": "org.springframework.security",
          "module": "spring-security-config",
          "version": {
            "requires": "6.5.3"
          }
        },
        {
          "group": "org.springframework.security",
          "module": "spring-security-web",
          "version": {
            "requires": "6.5.3"
          }
        },
        {
          "group": "org.springframework.kafka",
          "module": "spring-kafka",
          "version": {
            "requires": "3.3.10"
          }
        },
        {
          "group": "com.atomikos",
          "module": "transactions-spring-boot3-starter",
          "version": {
            "requires": "6.0.0"
          }
        },
        {
          "group": "io.jsonwebtoken",
          "module": "jjwt-api",
          "version": {
            "requires": "0.12.5"
          }
        },
        {
          "group": "org.springdoc",
          "module": "springdoc-openapi-starter-webmvc-ui",
          "version": {
            "requires": "2.8.6"
          }
        },
        {
          "group": "com.connection",
          "module": "token-shared",
          "version": {
            "requires": "1.0.0"
          }
        },
        {
          "group": "com.connection",
          "module": "connection-scheme-shared",
          "version": {
            "requires": "1.0.0"
          }
        },
        {
          "group": "com.connection",
          "module": "buffer-shared",
          "version": {
            "requires": "1.0.0"
          }
        },
        {
          "group": "com.connection",
          "module": "device-shared",
          "version": {
            "requires": "1.0.0"
          }
        },
        {
          "group": "com.connection",
          "module": "common-events",
          "version": {
            "requires": "1.0.0"
          }
        },
        {
          "group": "com.connection",
          "module": "common-auth-events",
          "version": {
            "requires": "1.0.0"
          }
        },
        {
          "group": "com.connection",
          "module": "common-device-events",
          "version": {
            "requires": "1.0.0"
          }
        },
        {
          "group": "com.connection",
          "module": "common-buffer-events",
          "version": {
            "requires": "1.0.0"
          }
        },
        {
          "group": "com.connection",
          "module": "common-connection-scheme-events",
          "version": {
            "requires": "1.0.0"
          }
        },
        {
          "group": "com.connection",
          "module": "auth-service",
          "version": {
            "requires": "1.0.0"
          }
        },
        {
          "group": "com.connection",
          "module": "connection-scheme-service",
          "version": {
            "requires": "1.0.0"
          }
        },
        {
          "group": "com.connection",
          "module": "device-service",
          "version": {
            "requires": "1.0.0"
          }
        },
        {
          "group": "org.postgresql",
          "module": "postgresql"
        },
        {
          "group": "io.jsonwebtoken",
          "module": "jjwt-impl",
          "version": {
            "requires": "0.12.5"
          }
        },
        {
          "group": "io.jsonwebtoken",
          "module": "jjwt-jackson",
          "version": {
            "requires": "0.12.5"
          }
        }
      ],
      "files": [
        {
          "name": "buffer-service-1.0.0-plain.jar",
          "url": "buffer-service-1.0.0-plain.jar",
          "size": 30786,
          "sha512": "210523b8b44a6062603b12c9bff0b8b5693d8413db1556c78480dea9608c05534a49f82dd33b3606ca701a26c0a57ffd02f0c3b739e37067be5a32fcc0be47f1",
          "sha256": "4599c205c30ae3cb205c2a5ef82520b40b1c398cb211eed83a23825a6b9028af",
          "sha1": "bf16b62f956e2aca8b2849c2c194c0ee649ed200",
          "md5": "8d74e3d5728b6b212486d4d45854fe47"
        }
      ]
    }
  ]
}
